cherrypyrest/__init__.py
cherrypyrest/crypto_utils.py
cherrypyrest/exceptions.py
cherrypyrest/fields.py
cherrypyrest/managers.py
cherrypyrest/messages.py
cherrypyrest/models.py
cherrypyrest/rest_apis.py
cherrypyrest/rest_serializers.py
cherrypyrest/utils.py
cherrypyrest-0.2.1.9.dist-info/LICENSE.txt
cherrypyrest-0.2.1.9.dist-info/METADATA
cherrypyrest-0.2.1.9.dist-info/WHEEL
cherrypyrest-0.2.1.9.dist-info/top_level.txt
cherrypyrest-0.2.1.9.dist-info/RECORD
