Metadata-Version: 2.1
Name: cherrypyrest
Version: 0.2.1.9
Summary: A REST like implementation of cherrypy
Home-page: https://github.com/umeshchaudhary/cherrypyrest
Author: Umesh Chaudhary
Author-email: 2umeshchaudhary@gmail.com
License: UNKNOWN
Download-URL: https://github.com/umeshchaudhary/cherrypyrest/archive/refs/tags/0.2.1.9.zip
Keywords: cherrypyrest RESTful cherrypy
Platform: UNKNOWN
Classifier: Development Status :: 4 - Beta
Classifier: Intended Audience :: Developers
Classifier: Topic :: Software Development :: Build Tools
Classifier: Programming Language :: Python :: 2.7
Requires-Dist: bson
Requires-Dist: cherrypy
Requires-Dist: mongomock
Requires-Dist: pycryptodome
Requires-Dist: pymongo
Requires-Dist: pytz
